pgjinja/__init__.py
pgjinja/pgjinja.py
pgjinja/pgjinja_async.py
pgjinja/schemas/__init__.py
pgjinja/schemas/pgjinja_settings.py
pgjinja/shared/__init__.py
pgjinja/shared/common.py
pgjinja-3.0.1.dist-info/METADATA
pgjinja-3.0.1.dist-info/WHEEL
pgjinja-3.0.1.dist-info/licenses/LICENSE
pgjinja-3.0.1.dist-info/RECORD
