Metadata-Version: 2.4
Name: pgjinja
Version: 3.0.1
Summary: A Python package that seamlessly integrates PostgreSQL, Jinja templating, and Pydantic for type-safe database queries
Project-URL: Homepage, https://github.com/tungph/pgjinja
Project-URL: Bug Tracker, https://github.com/tungph/pgjinja/issues
Project-URL: Documentation, https://github.com/tungph/pgjinja#readme
Project-URL: Source Code, https://github.com/tungph/pgjinja
Author-email: Shawn <shawn.dev.vn@gmail.com>
License: MIT
License-File: LICENSE
Keywords: async,database,jinja,postgresql,pydantic,sql,templates
Classifier: Development Status :: 4 - Beta
Classifier: Intended Audience :: Developers
Classifier: License :: OSI Approved :: MIT License
Classifier: Programming Language :: Python :: 3
Classifier: Programming Language :: Python :: 3.11
Classifier: Programming Language :: Python :: 3.12
Classifier: Programming Language :: Python :: 3.13
Classifier: Topic :: Database
Classifier: Topic :: Software Development :: Libraries :: Python Modules
Classifier: Typing :: Typed
Requires-Python: >=3.11
Requires-Dist: jinjasql2>=0.1.11
Requires-Dist: psycopg[binary,pool]>=3.2.6
Requires-Dist: pydantic>=2.10.6
